{
  "color": "YELLOW",
  "link": "https://bandauden.youtube73.repl.co/",
  "image": "https://cdn.discordapp.com/attachments/981839851135598633/981848743387217920/Mia_Quan_Ngu.png",
  "discord": "TThugs™#8554",
  "irl_name": "Lê Minh Quấn",
  "friendly_name": "Quân Ngu sImP cHúA mÊ mỀu SiMmY",
  "address": "",
  "phone_number": 12345678,
  "nationality": "Chinese",
  "date_of_birth": [9, 4, 2007],
  "gender": 2,
  "ig_name": "LiMoQua",
  "games": ["Roblox", "Ngọc Rồng Online"],
  "description": "Nóng như thế này thì làm sao phải mặc.",
  "school": "Trường Đời",
  "class": "Lớp chú Lộc Fuho",
  "intimacy": {
    "girl_friend": "Rất nhiều",
    "boy_friend": "Cũng rất nhiều",
    "best_friends": ["Cực kì nhiều"],
    "friends": ["Quá nhiều ko đếm xuể"]
  },
  "hidden": []
}